ytm2spt/__init__.py
ytm2spt/app_logger.py
ytm2spt/cli.py
ytm2spt/gui.py
ytm2spt/spotify.py
ytm2spt/transfer.py
ytm2spt/utils.py
ytm2spt/youtube.py
ytm2spt-1.1.2.dist-info/METADATA
ytm2spt-1.1.2.dist-info/WHEEL
ytm2spt-1.1.2.dist-info/entry_points.txt
ytm2spt-1.1.2.dist-info/licenses/LICENSE.md
ytm2spt-1.1.2.dist-info/RECORD
