Metadata-Version: 2.4
Name: ytm2spt
Version: 1.1.2
Summary: Transfer Playlists from YouTube Music to Spotify
Project-URL: Homepage, https://github.com/abhishekmj303/ytm2spt
Project-URL: Issues, https://github.com/abhishekmj303/ytm2spt/issues
Author-email: Abhishek M J <abhishekmj303@gmail.com>
License-File: LICENSE.md
Classifier: Development Status :: 5 - Production/Stable
Classifier: Environment :: Console
Classifier: Environment :: MacOS X
Classifier: Environment :: Win32 (MS Windows)
Classifier: Environment :: X11 Applications :: Qt
Classifier: Intended Audience :: End Users/Desktop
Classifier: License :: OSI Approved :: GNU General Public License v3 (GPLv3)
Classifier: Operating System :: OS Independent
Classifier: Programming Language :: Python :: 3.11
Classifier: Topic :: Internet
Classifier: Topic :: Multimedia :: Sound/Audio
Classifier: Topic :: Utilities
Requires-Python: >=3.11
Requires-Dist: pyside6>=6.8.0
Requires-Dist: spotipy>=2.24.0
Requires-Dist: thefuzz>=0.22.1
Requires-Dist: ytmusicapi==1.10.3
